pyromind_sdk/__init__.py
pyromind_sdk/node_sdk.py
pyromind_sdk-0.1.0.dist-info/licenses/LICENSE
pyromind_sdk-0.1.0.dist-info/METADATA
pyromind_sdk-0.1.0.dist-info/WHEEL
pyromind_sdk-0.1.0.dist-info/top_level.txt
pyromind_sdk-0.1.0.dist-info/RECORD
