Metadata-Version: 2.4
Name: pyromind-sdk
Version: 0.1.0
Summary: Lightweight SDK stub for local development and testing of third-party nodes without the full platform codebase
Author: PyroMind Team
License-Expression: MIT
Project-URL: Homepage, https://pyromind.ai/
Project-URL: Documentation, https://pyromind.ai/
Project-URL: Repository, https://github.com/pyromind/pyromind-sdk
Project-URL: Issues, https://github.com/pyromind/pyromind-sdk/issues
Keywords: sdk,node,development,stub
Classifier: Development Status :: 4 - Beta
Classifier: Intended Audience :: Developers
Classifier: Programming Language :: Python :: 3
Classifier: Programming Language :: Python :: 3.8
Classifier: Programming Language :: Python :: 3.9
Classifier: Programming Language :: Python :: 3.10
Classifier: Programming Language :: Python :: 3.11
Classifier: Programming Language :: Python :: 3.12
Classifier: Topic :: Software Development :: Libraries :: Python Modules
Requires-Python: >=3.8
License-File: LICENSE
Dynamic: license-file
